TestApp_Chanpreet-0.0.1.dist-info/METADATA
TestApp_Chanpreet-0.0.1.dist-info/RECORD
TestApp_Chanpreet-0.0.1.dist-info/WHEEL
TestApp_Chanpreet-0.0.1.dist-info/top_level.txt
app/__init__.py
app/module_one/__init__.py
app/module_one/controllers.py
app/module_one/models.py
app/templates/module_one/hello.html
