Metadata-Version: 2.1
Name: TestApp-Chanpreet
Version: 0.0.1
Summary: Useful towel-related stuff.
Home-page: http://pypi.python.org/pypi/TestApp-Chanpreet/
Author: Chanpreet Singh
Author-email: chanpreet.chhabra@gmail.com
License: UNKNOWN
Platform: UNKNOWN
Requires-Dist: flask
